{"name":"linkedin-shortcuts","tagline":"Userscript for keyboard shortcuts on LinkedIn.com","body":"### Description\r\nThis is a userscript using TamperMonkey on Google Chrome to bind Keyboard Shortcuts for [LinkedIn](http://linkedin.com).\r\n\r\n### Installation Steps (for Google Chrome)\r\n1. Add [TamperMonkey](http://bit.ly/12bWG6v) to Chrome\r\n2. Click to install the [linkedin-shortcuts userscript](http://bit.ly/1346q6d)\r\n\r\n### Keyboard Shortcuts\r\n|Key | Function |\r\n| ------------- | ------------- |\r\n| Alt + \\\t| Help (Pop-up) |\r\n| Alt + /\t| Main Search Box |\r\n| Alt + h\t| Navigate to Homepage |\r\n| Alt + p\t| Navigate to Profile Page |\r\n| Alt + i\t| Navigate to Invitations Page |\r\n| Alt + m\t| Navigate to Messages Page |\r\n| Alt + c\t| Navigate to Contacts Page |\r\n| Alt + w\t| Navigate to Who's View My Profile Page |\r\n| Alt + k\t| Navigate to People You May Know Page |\r\n| Alt + [1-5]\t| Navigate to Search Result # |\r\n\r\n### UserScript Details\r\n```\r\n// @name       linkedin-shortcuts\r\n// @namespace  http://danielfrancis.net/\r\n// @version    0.1\r\n// @description  Useful keyboard shortcuts for LinkedIn\r\n// @match      http://www.linkedin.com/*\r\n// @copyright  6-17-2013, Daniel Francis\r\n```\r\n","google":"UA-41823829-1","note":"Don't delete this file! It's used internally to help with page regeneration."}